dq/__init__.py
dq/account.py
dq/client.py
dq/error.py
dq/job.py
dq/request_client.py
dq/response.py
dq_batch_client-0.6.0.dist-info/AUTHORS.rst
dq_batch_client-0.6.0.dist-info/LICENSE
dq_batch_client-0.6.0.dist-info/METADATA
dq_batch_client-0.6.0.dist-info/WHEEL
dq_batch_client-0.6.0.dist-info/top_level.txt
dq_batch_client-0.6.0.dist-info/RECORD
