Metadata-Version: 2.1
Name: dq-batch-client
Version: 0.6.0
Summary: Python library which allows to use http://dataquality.pl in easy way.
Home-page: https://github.com/Algolytics/dq_batch_client
Author: Algolytics Technologies
Author-email: info@algolytics.pl
License: Apache Software License 2.0
Keywords: dataquality,dq,dq-batch-client
Classifier: Development Status :: 2 - Pre-Alpha
Classifier: Intended Audience :: Developers
Classifier: License :: OSI Approved :: Apache Software License
Classifier: Natural Language :: English
Classifier: Programming Language :: Python :: 3
Classifier: Programming Language :: Python :: 3.6
Classifier: Programming Language :: Python :: 3.7
Classifier: Programming Language :: Python :: 3.8
Classifier: Programming Language :: Python :: 3.9
Classifier: Programming Language :: Python :: 3.10
Classifier: Programming Language :: Python :: 3.11
Classifier: Programming Language :: Python :: 3.12
Classifier: Programming Language :: Python :: 3.13
Requires-Python: >=3.6
License-File: LICENSE
License-File: AUTHORS.rst
Requires-Dist: requests>=2.27.1
